testMail/__init__.py
testMail-2.0.dist-info/LICENSE
testMail-2.0.dist-info/METADATA
testMail-2.0.dist-info/WHEEL
testMail-2.0.dist-info/top_level.txt
testMail-2.0.dist-info/RECORD
