Metadata-Version: 2.1
Name: testMail
Version: 2.0
Summary: testing mail using smtp
Home-page: https://github.com/FKgk/testMail
Author: FKgk
Author-email: rhkd865@gmail.com
License: MIT
Platform: UNKNOWN
Classifier: Programming Language :: Python :: 3
Classifier: License :: OSI Approved :: MIT License
Classifier: Operating System :: OS Independent
